pr_keepachangelog/__init__.py
pr_keepachangelog/__main__.py
pr_keepachangelog/api/__init__.py
pr_keepachangelog/api/bitbucket_api.py
pr_keepachangelog/api/enums.py
pr_keepachangelog/api/pull_request_details.py
pr_keepachangelog/changelog/__init__.py
pr_keepachangelog/changelog/changelog.py
pr_keepachangelog/changelog/enums.py
pr_keepachangelog-1.0.11.dist-info/METADATA
pr_keepachangelog-1.0.11.dist-info/WHEEL
pr_keepachangelog-1.0.11.dist-info/entry_points.txt
pr_keepachangelog-1.0.11.dist-info/top_level.txt
pr_keepachangelog-1.0.11.dist-info/RECORD
