Metadata-Version: 2.1
Name: pr-keepachangelog
Version: 1.0.11
Summary: Add pull requests to changelog automatically with BitBucket pipelines and release changelog with keepachangelog.
Home-page: https://github.com/blackwiz4rd/pr-keepachangelog
Author: blackwiz4rd
Author-email: blackwiz4rd@gmail.com
License: MIT
Classifier: License :: OSI Approved :: MIT License
Classifier: Programming Language :: Python :: 3.10
Requires-Dist: keepachangelog (==2.0.0.dev2)
Requires-Dist: requests
Requires-Dist: python-dateutil
